setup.py
Gaussian_binomial_ML/Binomialdistribution.py
Gaussian_binomial_ML/Gaussiandistribution.py
Gaussian_binomial_ML/Generaldistribution.py
Gaussian_binomial_ML/__init__.py
Gaussian_binomial_ML.egg-info/PKG-INFO
Gaussian_binomial_ML.egg-info/SOURCES.txt
Gaussian_binomial_ML.egg-info/dependency_links.txt
Gaussian_binomial_ML.egg-info/not-zip-safe
Gaussian_binomial_ML.egg-info/top_level.txt