Metadata-Version: 1.0
Name: Gaussian-binomial-ML
Version: 0.1
Summary: Gaussian distributions
Home-page: UNKNOWN
Author: IkraP
Author-email: UNKNOWN
License: UNKNOWN
Platform: UNKNOWN
